torch_fourier_shift/__init__.py
torch_fourier_shift/dft_utils.py
torch_fourier_shift/fftfreq_grids.py
torch_fourier_shift/fourier_shift_dft.py
torch_fourier_shift/fourier_shift_image.py
torch_fourier_shift/phase_shift_grids.py
torch_fourier_shift-0.0.6.dist-info/METADATA
torch_fourier_shift-0.0.6.dist-info/WHEEL
torch_fourier_shift-0.0.6.dist-info/licenses/LICENSE
torch_fourier_shift-0.0.6.dist-info/RECORD
